{
  "_class": "bitmap",
  "clippingMask": "{{0, 0}, {1, 1}}",
  "do_objectID": "663B9470-7966-4B6F-910F-80371D738F76",
  "exportOptions": {
    "_class": "exportOptions",
    "exportFormats": [
    ],
    "includedLayerIds": [
    ],
    "layerOptions": 0,
    "shouldTrim": false
  },
  "fillReplacesImage": false,
  "frame": {
    "_class": "rect",
    "constrainProportions": true,
    "height": 233.3720314112082,
    "width": 151.6497572048793,
    "x": 66.35948947175712,
    "y": 190.4960505447571
  },
  "image": {
    "_class": "MSJSONFileReference",
    "_ref": "images/6c9a4d6b82cbe13886e57d64ffeb2f6a3cb6dde4",
    "_ref_class": "MSImageData"
  },
  "isFlippedHorizontal": false,
  "isFlippedVertical": false,
  "isLocked": false,
  "isVisible": true,
  "layerListExpandedType": 0,
  "name": "NV",
  "nameIsFixed": false,
  "nineSliceCenterRect": "{{0, 0}, {0, 0}}",
  "nineSliceScale": "{0, 0}",
  "resizingConstraint": 63,
  "resizingType": 0,
  "rotation": 0,
  "shouldBreakMaskChain": false,
  "style": {
    "_class": "style",
    "do_objectID": "EED77FC0-F723-405C-81F4-FAE88E45B064",
    "endDecorationType": 0,
    "fills": [
      {
        "_class": "fill",
        "color": {
          "_class": "color",
          "alpha": 1,
          "blue": 0.589510576180934,
          "green": 0.9510522959183674,
          "red": 0.7702814360496507
        },
        "fillType": 0,
        "gradient": {
          "_class": "gradient",
          "elipseLength": 1,
          "from": "{0.5, 0}",
          "gradientType": 2,
          "shouldSmoothenOpacity": false,
          "stops": [
            {
              "_class": "gradientStop",
              "color": {
                "_class": "color",
                "alpha": 1,
                "blue": 0.6661225649644228,
                "green": 0.9610785476799381,
                "red": 0.9908854166666666
              },
              "position": 0
            },
            {
              "_class": "gradientStop",
              "color": {
                "_class": "color",
                "alpha": 1,
                "blue": 0.4119099255469234,
                "green": 0.9080781235063693,
                "red": 0.9848533163265306
              },
              "position": 1
            }
          ],
          "to": "{0.5, 1}"
        },
        "isEnabled": true,
        "noiseIndex": 0,
        "noiseIntensity": 0,
        "patternFillType": 0,
        "patternTileScale": 1
      }
    ],
    "miterLimit": 10,
    "sharedObjectID": "BBDB8D97-7093-4501-A537-1FCE832D5D5E",
    "startDecorationType": 0
  }
}